MANIFEST.in
requirements.txt
setup.py
wscript
config/buildtools.cfg
config/compiler.cfg
config/defaults.cfg
config/externals.cfg
config/fnal-pkgs.cfg
config/larsoft.cfg
config/suite-art.cfg
config/suite-buildtools.cfg
config/suite-compiler.cfg
config/suite-externals.cfg
config/suite-larsoft.cfg
lbne_build.egg-info/PKG-INFO
lbne_build.egg-info/SOURCES.txt
lbne_build.egg-info/dependency_links.txt
lbne_build.egg-info/namespace_packages.txt
lbne_build.egg-info/requires.txt
lbne_build.egg-info/top_level.txt
patches/lbne/artdaqcore-1.04.07.patch
patches/lbne/cry-1.7.patch
patches/lbne/gccxml-0_9_20140718.patch
patches/lbne/modules-3.2.10.patch
patches/lbne/nutools-1.06.04.patch
patches/lbne/nutools-1.07.00.patch
patches/lbne/pandora-00.17.patch
patches/lbne/ppl-1.1.patch
patches/lbne/root-5.34.18.patch
patches/lbne/root-5.34.25.patch
worch/__init__.py
worch/lbne/__init__.py
worch/lbne/pandorasrc/__init__.py
worch/lbne/tbbinst/__init__.py