Metadata-Version: 1.0
Name: lbne-build
Version: 0.7.4
Summary: Worch/waf tools to build LBNE software.
Home-page: http://github.com/LBNE/lbne-build
Author: Brett Viren
Author-email: brett.viren@gmail.com
License: GPLv2
Platform: UNKNOWN
